LICENSE
MANIFEST.in
README.rst
setup.py
setup2.py
simpleui/.DS_Store
simpleui/__init__.py
simpleui/admin.py
simpleui/apps.py
simpleui/forms.py
simpleui/widgets.py
simpleui.egg-info/PKG-INFO
simpleui.egg-info/SOURCES.txt
simpleui.egg-info/dependency_links.txt
simpleui.egg-info/not-zip-safe
simpleui.egg-info/requires.txt
simpleui.egg-info/top_level.txt
simpleui/__pycache__/__init__.cpython-311.pyc
simpleui/__pycache__/__init__.cpython-312.pyc
simpleui/__pycache__/__init__.cpython-37.pyc
simpleui/__pycache__/__init__.cpython-38.pyc
simpleui/__pycache__/__init__.cpython-39.pyc
simpleui/__pycache__/__init__.pypy38.pyc
simpleui/__pycache__/admin.cpython-311.pyc
simpleui/__pycache__/admin.cpython-312.pyc
simpleui/__pycache__/admin.cpython-37.pyc
simpleui/__pycache__/admin.cpython-38.pyc
simpleui/__pycache__/admin.cpython-39.pyc
simpleui/__pycache__/admin.pypy38.pyc
simpleui/__pycache__/apps.cpython-311.pyc
simpleui/__pycache__/apps.cpython-312.pyc
simpleui/__pycache__/apps.cpython-37.pyc
simpleui/__pycache__/apps.cpython-38.pyc
simpleui/__pycache__/apps.cpython-39.pyc
simpleui/__pycache__/apps.pypy38.pyc
simpleui/__pycache__/forms.cpython-39.pyc
simpleui/__pycache__/widgets.cpython-39.pyc
simpleui/locale/zh_Hans/LC_MESSAGES/django.mo
simpleui/locale/zh_Hans/LC_MESSAGES/django.po
simpleui/locale/zh_Hans/LC_MESSAGES/make.sh
simpleui/static/.DS_Store
simpleui/static/admin/.DS_Store
simpleui/static/admin/simpleui-x/.DS_Store
simpleui/static/admin/simpleui-x/automatic/dicts.js
simpleui/static/admin/simpleui-x/automatic/segment.js
simpleui/static/admin/simpleui-x/css/base.css
simpleui/static/admin/simpleui-x/css/base.css.map
simpleui/static/admin/simpleui-x/css/base.less
simpleui/static/admin/simpleui-x/css/index.css
simpleui/static/admin/simpleui-x/css/index.css.map
simpleui/static/admin/simpleui-x/css/index.less
simpleui/static/admin/simpleui-x/css/login.css
simpleui/static/admin/simpleui-x/elementui/.DS_Store
simpleui/static/admin/simpleui-x/elementui/index.js
simpleui/static/admin/simpleui-x/elementui/locale/format.js
simpleui/static/admin/simpleui-x/elementui/locale/index.js
simpleui/static/admin/simpleui-x/elementui/locale/lang/af-ZA.js
